setup.py
delv/__init__.py
delv/archive.py
delv/colormap.py
delv/ddasm.py
delv/dscript.py
delv/graphics.py
delv/hints.py
delv/level.py
delv/library.py
delv/monster.py
delv/prop.py
delv/rdasm.py
delv/rdasm_symbolics.py
delv/script.py
delv/sound.py
delv/store.py
delv/tile.py
delv/types.py
delv/util.py
delv.egg-info/PKG-INFO
delv.egg-info/SOURCES.txt
delv.egg-info/dependency_links.txt
delv.egg-info/requires.txt
delv.egg-info/top_level.txt
delv/rdasm_include/Cythera.rdasm
delv/rdasm_include/Delver/Main.rdasm
delv/rdasm_include/Delver/Model.rdasm