Metadata-Version: 1.1
Name: delv
Version: 0.2.2
Summary: Module for making tools interoperable with Delver
Home-page: http://www.ferazelhosting.net/wiki/delv
Author: Bryce Schroeder
Author-email: bryce.schroeder@gmail.com
License: GPL-3
Platform: UNKNOWN
Classifier: Development Status :: 3 - Alpha
Classifier: License :: OSI Approved :: GNU General Public License v3 or later (GPLv3+)
Classifier: Topic :: Games/Entertainment :: Role-Playing
